graiax_sayamod_record/.git/COMMIT_EDITMSG
graiax_sayamod_record/.git/config
graiax_sayamod_record/.git/description
graiax_sayamod_record/.git/HEAD
graiax_sayamod_record/.git/hooks/applypatch-msg.sample
graiax_sayamod_record/.git/hooks/commit-msg.sample
graiax_sayamod_record/.git/hooks/fsmonitor-watchman.sample
graiax_sayamod_record/.git/hooks/post-update.sample
graiax_sayamod_record/.git/hooks/pre-applypatch.sample
graiax_sayamod_record/.git/hooks/pre-commit.sample
graiax_sayamod_record/.git/hooks/pre-merge-commit.sample
graiax_sayamod_record/.git/hooks/pre-push.sample
graiax_sayamod_record/.git/hooks/pre-rebase.sample
graiax_sayamod_record/.git/hooks/pre-receive.sample
graiax_sayamod_record/.git/hooks/prepare-commit-msg.sample
graiax_sayamod_record/.git/hooks/push-to-checkout.sample
graiax_sayamod_record/.git/hooks/update.sample
graiax_sayamod_record/.git/index
graiax_sayamod_record/.git/info/exclude
graiax_sayamod_record/.git/logs/HEAD
graiax_sayamod_record/.git/logs/refs/heads/main
graiax_sayamod_record/.git/objects/0c/63263259df09ec3e0d0718b9b88c656356d1e6
graiax_sayamod_record/.git/objects/21/92045706fb47bc6dcfab502ffdd68ebe232131
graiax_sayamod_record/.git/objects/22/50605e21b71ae298eb8b89c76cbd22513f718e
graiax_sayamod_record/.git/objects/3b/ffb06ccfb04d7bd4383dd339bae1dc177fe11f
graiax_sayamod_record/.git/objects/3d/a14e2bd1650f98eda8154fb210bef79fadb0ce
graiax_sayamod_record/.git/objects/8c/9e78721f97abe443c579de4803ef9744d2e906
graiax_sayamod_record/.git/objects/93/f82600868d8235917ed7ac2763303695fef7eb
graiax_sayamod_record/.git/objects/9c/6c9c839cadf6d43da143cf0e3010301f785b8a
graiax_sayamod_record/.git/objects/ae/c3db4939654abc54dd96f2db492061801022b1
graiax_sayamod_record/.git/objects/b4/495cf8b56081e4d4cdb13b9830216ef36ead54
graiax_sayamod_record/.git/objects/c1/ea9368147cf00d2bae1448bcb92ff1967f2495
graiax_sayamod_record/.git/objects/db/f2e4f8927e86765bc7ef9a01ebacda9eece9b4
graiax_sayamod_record-0.3.1.dist-info/WHEEL
graiax_sayamod_record-0.3.1.dist-info/METADATA
graiax_sayamod_record-0.3.1.dist-info/RECORD
