Metadata-Version: 2.1
Name: graiax-sayamod-record
Version: 0.3.1
Summary: A graia saya mod to record message in databases.
License: AGPL-3.0
Author: hans
Author-email: dxzenghan@163.com
Requires-Python: >=3.8,<4.0
Classifier: License :: OSI Approved :: GNU Affero General Public License v3
Classifier: Programming Language :: Python :: 3
Classifier: Programming Language :: Python :: 3.8
Classifier: Programming Language :: Python :: 3.9
Requires-Dist: graia-application-mirai (>=0.17.0,<0.18.0)
Requires-Dist: graia-broadcast (>=0.7.0,<0.8.0)
Requires-Dist: graia-saya (>=0.0.9,<0.0.10)
Requires-Dist: pony (>=0.7.14,<0.8.0)
